purify/__about__.py
purify/__init__.py
purify/purify.py
purify/py.typed
purify-0.2.3.dist-info/LICENSE
purify-0.2.3.dist-info/METADATA
purify-0.2.3.dist-info/WHEEL
purify-0.2.3.dist-info/top_level.txt
purify-0.2.3.dist-info/RECORD
