Metadata-Version: 2.1
Name: purify
Version: 0.2.3
Summary: Pythonic object-mutator transforms as pure functions
Home-page: https://github.com/xoeye/purify
Author: Peter Gaultney
Author-email: pgaultney@xoi.io
License: UNKNOWN
Platform: UNKNOWN
Requires-Python: >=3.7
License-File: LICENSE
